webfaction_fab2-0.0.1.dist-info/METADATA
webfaction_fab2-0.0.1.dist-info/RECORD
webfaction_fab2-0.0.1.dist-info/WHEEL
webfaction_fab2-0.0.1.dist-info/top_level.txt
wf_fab2/connection.py
wf_fab2/fabfile.py
wf_fab2/makefab.py
wf_fab2/ssl_certs.py
wf_fab2/util.py
wf_fab2/websites.py
