Metadata-Version: 2.1
Name: webfaction-fab2
Version: 0.0.1
Summary: Scripts to help provision, configure and deply towebfaction using Python and Fabric 2
Home-page: https://github.com/moaxey/wf_fab2
Author: Mathew Oakes
Author-email: open@mathewoak.es
License: MIT
Platform: UNKNOWN
Classifier: Development Status :: 3 - Alpha
Classifier: Programming Language :: Python :: 3 :: Only
Classifier: Programming Language :: Python :: 3.6
Classifier: Programming Language :: Python :: 3.7
Classifier: Intended Audience :: Developers
Classifier: License :: OSI Approved :: MIT License
Requires-Python: >3.6
Requires-Dist: fabric
Requires-Dist: dnspython
Requires-Dist: requests
